tolonteria/__init__.py
tolonteria/roms.py
tolonteria-0.0.1.dist-info/METADATA
tolonteria-0.0.1.dist-info/WHEEL
tolonteria-0.0.1.dist-info/top_level.txt
tolonteria-0.0.1.dist-info/RECORD
